PyBusiness/__init__.py
PyBusiness-0.1.0.dist-info/METADATA
PyBusiness-0.1.0.dist-info/RECORD
PyBusiness-0.1.0.dist-info/WHEEL
PyBusiness-0.1.0.dist-info/top_level.txt
