Metadata-Version: 2.1
Name: PyBusiness
Version: 0.1.0
Summary: An easy way to use domesticated utilities for purposes such as business
Home-page: https://saythanks-com-python-email.webnode.com
Author: J. Nma
Author-email: wooldoughnutspi@gmail.com
License: MIT
Project-URL: Documentation, https://packaging.python.org/tutorials/distributing-packages/
Project-URL: Funding, https://donate.pypi.org
Project-URL: Say Thanks!, https://saythanks-com-python-email.webnode.com
Project-URL: Source, https://saythanks-com-python-email.webnode.com
Keywords: personal_use business_use multi-purpose business
Platform: UNKNOWN
Classifier: Development Status :: 3 - Alpha
Classifier: Programming Language :: Python :: 3
Classifier: License :: OSI Approved :: MIT License
Classifier: Operating System :: OS Independent
Requires-Python: >=3
